{
    "@class": "com.kony.gen.viz.model.component.KVizLabel",
    "DNDConfig": null,
    "__parentReadjusting__": false,
    "_height_": {
        "type": "ref",
        "value": "preferred"
    },
    "_left_": {
        "type": "string",
        "value": "15dp"
    },
    "_margin_": [
        1,
        1,
        1,
        1
    ],
    "_padding_": [
        0,
        0,
        0,
        0
    ],
    "_skin_": "s65091c77ce44fb6bee4903c9e516c3d",
    "_text_": "Employee",
    "_width_": {
        "type": "ref",
        "value": "preferred"
    },
    "_wrapping_": 2,
    "android": {
        "textStyle": {
            "letterSpacing": 0,
            "strikeThrough": false
        }
    },
    "canUpdateUI": true,
    "centery": {
        "type": "string",
        "value": "50%"
    },
    "containerId": true,
    "containerweight": 100,
    "contentalignment": 4,
    "id": "lblEmployeeHeader",
    "info": null,
    "ipad": {
        "psp": {
            "wrapping": 2
        }
    },
    "iphone": {
        "psp": {
            "wrapping": 2
        }
    },
    "isvisible": true,
    "kuid": "cb8c22d6c7db430b99a131ed8b8cd15d",
    "name": "kony.ui.Label",
    "parent": "flxEmployeeHeader",
    "pf": "tempSegTeamViewHeader31",
    "tooltip": "",
    "wType": "Label",
    "zindex": 1
}