{
    "@class": "com.kony.gen.viz.model.component.KVizLabel",
    "DNDConfig": null,
    "__parentReadjusting__": false,
    "_height_": {
        "type": "ref",
        "value": "preferred"
    },
    "_left_": {
        "type": "string",
        "value": "55%"
    },
    "_margin_": [
        1,
        1,
        1,
        1
    ],
    "_padding_": [
        0,
        0,
        0,
        0
    ],
    "_skin_": "s73468a2178d44f0964dd96b7c698dcd",
    "_text_": "New Year",
    "_top_": {
        "type": "string",
        "value": "10dp"
    },
    "_width_": {
        "type": "ref",
        "value": "preferred"
    },
    "_wrapping_": 2,
    "android": {
        "textStyle": {
            "letterSpacing": 0,
            "strikeThrough": false
        }
    },
    "canUpdateUI": true,
    "containerId": true,
    "containerweight": 100,
    "contentalignment": 4,
    "id": "lblHolidayName",
    "info": null,
    "ipad": {
        "psp": {
            "wrapping": 2
        }
    },
    "iphone": {
        "psp": {
            "wrapping": 2
        }
    },
    "isvisible": true,
    "kuid": "99db4f88e73e4a72857e3e3bc86e915b",
    "name": "kony.ui.Label",
    "parent": "flxSegAllEventsList",
    "pf": "tempSegAllEventsList",
    "tooltip": "",
    "wType": "Label",
    "zindex": 1
}