{
    "@class": "com.kony.gen.viz.model.component.KVizLabel",
    "DNDConfig": null,
    "__parentReadjusting__": false,
    "_height_": {
        "type": "ref",
        "value": "preferred"
    },
    "_left_": {
        "type": "string",
        "value": "78%"
    },
    "_margin_": [
        1,
        1,
        1,
        1
    ],
    "_padding_": [
        1,
        0,
        1,
        0
    ],
    "_skin_": "s79421f705f24dbfaf1772878c1cf466",
    "_text_": "DELEGATED",
    "_top_": {
        "type": "string",
        "value": "16%"
    },
    "_width_": {
        "type": "ref",
        "value": "preferred"
    },
    "_wrapping_": 2,
    "android": {
        "textStyle": {
            "letterSpacing": 0,
            "strikeThrough": false
        }
    },
    "canUpdateUI": true,
    "containerweight": 100,
    "contentalignment": 4,
    "id": "lblDelegate",
    "info": null,
    "ipad": {
        "psp": {
            "wrapping": 2
        }
    },
    "iphone": {
        "psp": {
            "wrapping": 2
        }
    },
    "isvisible": true,
    "kuid": "57c00498d2a74660a5e42144cd49c537",
    "name": "kony.ui.Label",
    "paddinginpixel": false,
    "parent": "flxTimeRequest",
    "pf": "frmApprovalsDashboard",
    "tooltip": "",
    "wType": "Label",
    "zindex": 1
}