{
    "@class": "com.kony.gen.viz.model.component.KVizImage2",
    "DNDConfig": null,
    "__parentReadjusting__": false,
    "_base64_": null,
    "_height_": {
        "type": "string",
        "value": "43dp"
    },
    "_margin_": [
        0,
        0,
        0,
        0
    ],
    "_padding_": [
        0,
        0,
        0,
        0
    ],
    "_skin_": "s82580abaae041919a6f0dcd806a8358",
    "_src_": "add_task.png",
    "_top_": {
        "type": "string",
        "value": "0dp"
    },
    "_width_": {
        "type": "string",
        "value": "43dp"
    },
    "canUpdateUI": true,
    "centerx": {
        "type": "string",
        "value": "50%"
    },
    "containerweight": 100,
    "context": {
        "channel": "desktop",
        "formID": "frmCreateViewDW",
        "platform": "desktopweb",
        "templateType": "forms",
        "topLevelBox": null
    },
    "id": "imgAddNewTaskRight",
    "imagescalemode": 1,
    "info": null,
    "isvisible": true,
    "kuid": "97c258f400534b1f80eb07fef8c5fe66",
    "name": "kony.ui.Image2",
    "parent": "flxAddNewTaskRight",
    "pf": "frmCreateViewDW",
    "srcType": 1,
    "wType": "Image",
    "widgetalignment": 5,
    "zindex": 1
}