{
    "DNDConfig": null,
    "__parentReadjusting__": false,
    "_height_": {
        "type": "string",
        "value": "87.95%"
    },
    "_left_": {
        "type": "string",
        "value": "0%"
    },
    "_margin_": [
        0,
        0,
        0,
        0
    ],
    "_orientation_": 6,
    "_padding_": [
        0,
        0,
        0,
        0
    ],
    "_percent_": true,
    "_skin_": "s83d658e470f40a79ff731433754c0a7",
    "_top_": {
        "type": "string",
        "value": "12%"
    },
    "_width_": {
        "type": "string",
        "value": "58.59%"
    },
    "allboxes": [],
    "autogrowmode": 0,
    "canUpdateUI": true,
    "children": [
        "segPendingList"
    ],
    "clipbounds": true,
    "containerweight": 100,
    "enablescrolling": true,
    "id": "flxPendingList",
    "info": null,
    "isvisible": true,
    "kuid": "68a80cf89c2a433486ab6c26f2addb8a",
    "layouttype": 2,
    "name": "kony.ui.FlexContainer",
    "parent": "flxComplete",
    "pf": "frmTabPendingList",
    "snapgridsize": 10,
    "snaptogrid": true,
    "wType": "FlexContainer",
    "widgetalignment": 1,
    "zindex": 1
}