{
  "android": {
    "background_color": "ff6e5fff",
    "bg_type": "one",
    "font_color": "ffffffff",
    "font_name": "Helvetica",
    "font_size": 132,
    "isForked": true
  },
  "background_color": "6ebeaaff",
  "bg_type": "one",
  "border_color": "424242ff",
  "border_style": "plain",
  "border_type": 0,
  "border_width": 1,
  "desktopweb": {
    "background_color": "ff6e5fff",
    "bg_type": "one",
    "border_type": 0,
    "bottom_left_border_color": "42424200",
    "bottom_left_border_radius": "100",
    "bottom_left_border_style": "rc",
    "bottom_left_border_width": 1,
    "bottom_right_border_color": "42424200",
    "bottom_right_border_radius": "100",
    "bottom_right_border_style": "rc",
    "bottom_right_border_width": 1,
    "font_color": "ffffffff",
    "font_name": "AvenirLTStd-Roman",
    "font_size": 132,
    "isForked": true,
    "top_left_border_color": "42424200",
    "top_left_border_radius": "100",
    "top_left_border_style": "rc",
    "top_left_border_width": 1,
    "top_right_border_color": "42424200",
    "top_right_border_radius": "100",
    "top_right_border_style": "rc",
    "top_right_border_width": 1
  },
  "fontSizeInPx": false,
  "font_color": "424242ff",
  "font_name": "Helvetica",
  "font_size": 214,
  "font_style": "normal",
  "font_weight": "normal",
  "ipad": {
    "background_color": "ff6e5fff",
    "bg_type": "one",
    "font_color": "ffffffff",
    "font_name": "Helvetica",
    "font_size": 132,
    "isForked": true
  },
  "iphone": {
    "background_color": "ff6e5fff",
    "bg_type": "one",
    "font_color": "ffffffff",
    "font_name": "Helvetica",
    "font_size": 132,
    "isForked": true
  },
  "isDefaultSkin": false,
  "kiosk": {
    "background_color": "ff6e5fff",
    "bg_type": "one",
    "font_color": "ffffffff",
    "font_name": "GenericMonospace",
    "font_size": 132,
    "isForked": true
  },
  "kuid": "s3f5f42d0dee43b8bfb39c8a69929ca0",
  "spaan": {
    "background_color": "ff6e5fff",
    "bg_type": "one",
    "border_type": 0,
    "bottom_left_border_color": "42424200",
    "bottom_left_border_radius": "100",
    "bottom_left_border_style": "rc",
    "bottom_left_border_width": 1,
    "bottom_right_border_color": "42424200",
    "bottom_right_border_radius": "100",
    "bottom_right_border_style": "rc",
    "bottom_right_border_width": 1,
    "font_color": "ffffffff",
    "font_name": "Helvetica",
    "font_size": 132,
    "isForked": true,
    "top_left_border_color": "42424200",
    "top_left_border_radius": "100",
    "top_left_border_style": "rc",
    "top_left_border_width": 1,
    "top_right_border_color": "42424200",
    "top_right_border_radius": "100",
    "top_right_border_style": "rc",
    "top_right_border_width": 1
  },
  "spaandroidtablet": {
    "background_color": "ff6e5fff",
    "bg_type": "one",
    "border_type": 0,
    "bottom_left_border_color": "42424200",
    "bottom_left_border_radius": "100",
    "bottom_left_border_style": "rc",
    "bottom_left_border_width": 1,
    "bottom_right_border_color": "42424200",
    "bottom_right_border_radius": "100",
    "bottom_right_border_style": "rc",
    "bottom_right_border_width": 1,
    "font_color": "ffffffff",
    "font_name": "Helvetica",
    "font_size": 132,
    "isForked": true,
    "top_left_border_color": "42424200",
    "top_left_border_radius": "100",
    "top_left_border_style": "rc",
    "top_left_border_width": 1,
    "top_right_border_color": "42424200",
    "top_right_border_radius": "100",
    "top_right_border_style": "rc",
    "top_right_border_width": 1
  },
  "spabb": {
    "background_color": "ff6e5fff",
    "bg_type": "one",
    "border_type": 0,
    "bottom_left_border_color": "42424200",
    "bottom_left_border_radius": "100",
    "bottom_left_border_style": "rc",
    "bottom_left_border_width": 1,
    "bottom_right_border_color": "42424200",
    "bottom_right_border_radius": "100",
    "bottom_right_border_style": "rc",
    "bottom_right_border_width": 1,
    "font_color": "ffffffff",
    "font_name": "Helvetica",
    "font_size": 132,
    "isForked": true,
    "top_left_border_color": "42424200",
    "top_left_border_radius": "100",
    "top_left_border_style": "rc",
    "top_left_border_width": 1,
    "top_right_border_color": "42424200",
    "top_right_border_radius": "100",
    "top_right_border_style": "rc",
    "top_right_border_width": 1
  },
  "spaip": {
    "background_color": "ff6e5fff",
    "bg_type": "one",
    "border_type": 0,
    "bottom_left_border_color": "42424200",
    "bottom_left_border_radius": "100",
    "bottom_left_border_style": "rc",
    "bottom_left_border_width": 1,
    "bottom_right_border_color": "42424200",
    "bottom_right_border_radius": "100",
    "bottom_right_border_style": "rc",
    "bottom_right_border_width": 1,
    "font_color": "ffffffff",
    "font_name": "Helvetica",
    "font_size": 132,
    "isForked": true,
    "top_left_border_color": "42424200",
    "top_left_border_radius": "100",
    "top_left_border_style": "rc",
    "top_left_border_width": 1,
    "top_right_border_color": "42424200",
    "top_right_border_radius": "100",
    "top_right_border_style": "rc",
    "top_right_border_width": 1
  },
  "spaipad": {
    "background_color": "ff6e5fff",
    "bg_type": "one",
    "border_type": 0,
    "bottom_left_border_color": "42424200",
    "bottom_left_border_radius": "100",
    "bottom_left_border_style": "rc",
    "bottom_left_border_width": 1,
    "bottom_right_border_color": "42424200",
    "bottom_right_border_radius": "100",
    "bottom_right_border_style": "rc",
    "bottom_right_border_width": 1,
    "font_color": "ffffffff",
    "font_name": "Helvetica",
    "font_size": 132,
    "isForked": true,
    "top_left_border_color": "42424200",
    "top_left_border_radius": "100",
    "top_left_border_style": "rc",
    "top_left_border_width": 1,
    "top_right_border_color": "42424200",
    "top_right_border_radius": "100",
    "top_right_border_style": "rc",
    "top_right_border_width": 1
  },
  "spawindowstablet": {
    "background_color": "ff6e5fff",
    "bg_type": "one",
    "border_type": 0,
    "bottom_left_border_color": "42424200",
    "bottom_left_border_radius": "100",
    "bottom_left_border_style": "rc",
    "bottom_left_border_width": 1,
    "bottom_right_border_color": "42424200",
    "bottom_right_border_radius": "100",
    "bottom_right_border_style": "rc",
    "bottom_right_border_width": 1,
    "font_color": "ffffffff",
    "font_name": "Helvetica",
    "font_size": 132,
    "isForked": true,
    "top_left_border_color": "42424200",
    "top_left_border_radius": "100",
    "top_left_border_style": "rc",
    "top_left_border_width": 1,
    "top_right_border_color": "42424200",
    "top_right_border_radius": "100",
    "top_right_border_style": "rc",
    "top_right_border_width": 1
  },
  "spawinphone8": {
    "background_color": "ff6e5fff",
    "bg_type": "one",
    "border_type": 0,
    "bottom_left_border_color": "42424200",
    "bottom_left_border_radius": "100",
    "bottom_left_border_style": "rc",
    "bottom_left_border_width": 1,
    "bottom_right_border_color": "42424200",
    "bottom_right_border_radius": "100",
    "bottom_right_border_style": "rc",
    "bottom_right_border_width": 1,
    "font_color": "ffffffff",
    "font_name": "Helvetica",
    "font_size": 132,
    "isForked": true,
    "top_left_border_color": "42424200",
    "top_left_border_radius": "100",
    "top_left_border_style": "rc",
    "top_left_border_width": 1,
    "top_right_border_color": "42424200",
    "top_right_border_radius": "100",
    "top_right_border_style": "rc",
    "top_right_border_width": 1
  },
  "tabrcandroid": {
    "background_color": "ff6e5fff",
    "bg_type": "one",
    "font_color": "ffffffff",
    "font_name": "Helvetica",
    "font_size": 132,
    "isForked": true
  },
  "wType": "Label",
  "watchos": {
    "font_color": "ffffffff",
    "font_name": "Helvetica",
    "font_size": 132,
    "isForked": true
  },
  "windows8": {
    "background_color": "ff6e5fff",
    "bg_type": "one",
    "font_color": "ffffffff",
    "font_name": "AvenirLTStd-Black",
    "font_size": 132,
    "isForked": true
  },
  "winphone8": {
    "background_color": "ff6e5fff",
    "bg_type": "one",
    "font_color": "ffffffff",
    "font_name": "GenericMonospace",
    "font_size": 132,
    "isForked": true
  }
}