{
    "AS_FlexContainer_7ac7454d11ed4ffa9acd1955cff940af": {
        "id": "AS_FlexContainer_7ac7454d11ed4ffa9acd1955cff940af",
        "type": "ACTION_SEQUENCE",
        "name": "OntempListClick",
        "params": [{
            "datatype": "collection",
            "name": "eventobject"
        }, {
            "datatype": "collection",
            "name": "context"
        }],
        "contextObj": {
            "name": "tmpListDetailsDW",
            "type": "templates",
            "platform": "",
            "KUID": "1011751a6c1940e1846c4be4b8fbb6fe"
        },
        "language": "js",
        "actions": [{
            "id": "ADD_SNIPPET__3a6191acc6ab4260a6bae5aea7ba8e81",
            "type": "ADD_SNIPPET",
            "codeSnippet": "",
            "parentId": null,
            "callbackType": null
        }]
    }
}