{
    "AS_Button_9ea4697ece9a4449b9ea2562e4aea3d2": {
        "id": "AS_Button_9ea4697ece9a4449b9ea2562e4aea3d2",
        "type": "ACTION_SEQUENCE",
        "name": "actionOnClickOfLoginBtnOnFrmStartupTab",
        "params": [{
            "datatype": "collection",
            "name": "eventobject"
        }],
        "contextObj": {
            "name": "frmStartUp",
            "type": "forms",
            "platform": null,
            "KUID": "0832e7aaaf2e4397a9e062b491d2d23b"
        },
        "language": "js",
        "actions": [{
            "id": "ADD_SNIPPET__663118f2ba32426eab89e5eae52f0dcb",
            "type": "ADD_SNIPPET",
            "codeSnippet": "frmLogin.show();",
            "parentId": null,
            "callbackType": null
        }]
    }
}