{
    "AS_FlexContainer_35e8e9b567bc404ea6ddf4253525ec6e": {
        "id": "AS_FlexContainer_35e8e9b567bc404ea6ddf4253525ec6e",
        "type": "ACTION_SEQUENCE",
        "name": "actWinListSearch",
        "params": [{
            "datatype": "collection",
            "name": "eventobject"
        }],
        "language": "js",
        "actions": [{
            "id": "ADD_SNIPPET_ide_onClick_0015b679451249f784a1285afb0cfd3e",
            "type": "ADD_SNIPPET",
            "codeSnippet": "kony.apps.coe.ess.Approvals.DynamicSegmentSetDatabyEmployeeHasApprovalRequests(kony.apps.coe.ess.globalVariables.FrmApprovalsPeopleSearch);\nfrmTabListView.flxEmployeeSearch.setVisibility(true);",
            "callbackType": null
        }]
    }
}