{
    "AS_Button_1445506675e349aaaed04f81fd9a9eae": {
        "id": "AS_Button_1445506675e349aaaed04f81fd9a9eae",
        "type": "ACTION_SEQUENCE",
        "name": "tabWinApplyFilterAction",
        "params": [{
            "datatype": "collection",
            "name": "eventobject"
        }],
        "contextObj": {
            "name": "frmTabApprovalHistory",
            "type": "forms",
            "platform": "",
            "KUID": "486c20b1d92c44ba9cd4d5054648e273"
        },
        "language": "js",
        "actions": [{
            "id": "ADD_SNIPPET__892daa5da9dc45c5a6ac5a6144186b42",
            "type": "ADD_SNIPPET",
            "codeSnippet": "(new kony.apps.coe.ess.ApprovalHistoryTab()).filterApplyOnClick();",
            "parentId": null,
            "callbackType": null
        }]
    }
}