{
    "AS_FlexContainer_c822504c1bbf4e23bf7d162f03835772": {
        "id": "AS_FlexContainer_c822504c1bbf4e23bf7d162f03835772",
        "type": "ACTION_SEQUENCE",
        "name": "tabWinViewHistoryReject",
        "params": [{
            "datatype": "collection",
            "name": "eventobject"
        }],
        "language": "js",
        "actions": [{
            "id": "ADD_SNIPPET_ide_onClick_32028f698c9645249b26d916a7e062f0",
            "type": "ADD_SNIPPET",
            "codeSnippet": "(new kony.apps.coe.ess.Approvals.getApprovalsRequestList()).onClickReject();",
            "callbackType": null
        }]
    }
}