{
    "DNDConfig": null,
    "_height_": {
        "type": "string",
        "value": "20%"
    },
    "_margin_": [
        0,
        0,
        0,
        0
    ],
    "_orientation_": 6,
    "_padding_": [
        0,
        0,
        0,
        0
    ],
    "_percent_": true,
    "_skin_": "s2cc5749eea84023bc820a043bb65e9a",
    "allboxes": [],
    "autogrowmode": 0,
    "canUpdateUI": true,
    "children": [
        "lblTaskDuration",
        "lblHours",
        "flxBorder"
    ],
    "clipbounds": true,
    "containerId": true,
    "containerweight": 100,
    "enablescrolling": true,
    "id": "flxTaskDuration",
    "info": null,
    "isTemplate": true,
    "isvisible": true,
    "kuid": "47df90fa67b64b8a978898b2e9b7d39a",
    "layouttype": 2,
    "name": "kony.ui.FlexContainer",
    "parent": "tempSegReviewTasks",
    "pf": "tempSegReviewTasks",
    "snapgridsize": 10,
    "snaptogrid": true,
    "wType": "FlexContainer",
    "widgetalignment": 1
}