{
    "@class": "com.kony.gen.viz.model.component.KVizLabel",
    "DNDConfig": null,
    "__parentReadjusting__": false,
    "_height_": {
        "type": "ref",
        "value": "preferred"
    },
    "_margin_": [
        1,
        1,
        1,
        1
    ],
    "_padding_": [
        0,
        0,
        0,
        0
    ],
    "_skin_": "sc6f1bcf9c7549fd9124b8abc0c5ff56",
    "_text_": "",
    "_width_": {
        "type": "ref",
        "value": "preferred"
    },
    "_wrapping_": 2,
    "android": {
        "textStyle": {
            "letterSpacing": 0,
            "strikeThrough": false
        }
    },
    "canUpdateUI": true,
    "centerx": {
        "type": "string",
        "value": "50%"
    },
    "centery": {
        "type": "string",
        "value": "49.98%"
    },
    "containerweight": 100,
    "contentalignment": 4,
    "id": "lblClearSrcScreen",
    "info": null,
    "ipad": {
        "psp": {
            "wrapping": 2
        }
    },
    "iphone": {
        "psp": {
            "wrapping": 2
        }
    },
    "isvisible": true,
    "kuid": "97be01920519430b95a8655bf8417bb0",
    "name": "kony.ui.Label",
    "parent": "flxClearSrcScreen",
    "pf": "frmSearch",
    "texti18n": "i18n.ess.MyApprovals.frmSearch.lblClearSrcScreen",
    "tooltip": "",
    "wType": "Label",
    "zindex": 1
}