{
    "@class": "com.kony.gen.viz.model.component.KVizLabel",
    "DNDConfig": null,
    "__parentReadjusting__": false,
    "_height_": {
        "type": "ref",
        "value": "preferred"
    },
    "_margin_": [
        1,
        1,
        1,
        1
    ],
    "_padding_": [
        1,
        0,
        1,
        0
    ],
    "_skin_": "s1e8c65080c34076b05fcacb4b892abf",
    "_text_": "1 Nov - 7 Nov",
    "_width_": {
        "type": "ref",
        "value": "preferred"
    },
    "_wrapping_": 2,
    "android": {
        "textStyle": {
            "letterSpacing": 0,
            "strikeThrough": false
        }
    },
    "canUpdateUI": true,
    "centerx": {
        "type": "string",
        "value": "50%"
    },
    "centery": {
        "type": "string",
        "value": "50%"
    },
    "containerId": true,
    "containerweight": 100,
    "contentalignment": 5,
    "id": "lblWeek",
    "info": null,
    "ipad": {
        "psp": {
            "wrapping": 2
        }
    },
    "iphone": {
        "psp": {
            "wrapping": 2
        }
    },
    "isvisible": true,
    "kuid": "0470325ec70f4b479c5e6f8c61fc86f2",
    "name": "kony.ui.Label",
    "paddinginpixel": false,
    "parent": "flxWeek",
    "pf": "tmpListDetailsDW",
    "tooltip": "",
    "wType": "Label",
    "zindex": 1
}