{
    "@class": "com.kony.gen.viz.model.component.KVizLabel",
    "DNDConfig": null,
    "__parentReadjusting__": false,
    "_height_": {
        "type": "ref",
        "value": "preferred"
    },
    "_left_": {
        "type": "string",
        "value": "2.30%"
    },
    "_margin_": [
        1,
        1,
        1,
        1
    ],
    "_padding_": [
        4,
        1,
        4,
        1
    ],
    "_skin_": "se532155365b47ef930672d93dd7fea8",
    "_text_": "",
    "_width_": {
        "type": "ref",
        "value": "preferred"
    },
    "_wrapping_": 2,
    "android": {
        "textStyle": {
            "letterSpacing": 0,
            "strikeThrough": false
        }
    },
    "canUpdateUI": true,
    "centery": {
        "type": "string",
        "value": "50%"
    },
    "containerweight": 100,
    "contentalignment": 4,
    "id": "lblAll",
    "ide_onTouchEnd": "AS_Label_b133ac0d8be94bebab93c081a495285b",
    "info": null,
    "ipad": {
        "psp": {
            "wrapping": 2
        }
    },
    "iphone": {
        "psp": {
            "wrapping": 2
        }
    },
    "isvisible": true,
    "kuid": "5e82159d58394792ada68922e5ffe723",
    "name": "kony.ui.Label",
    "paddinginpixel": false,
    "parent": "flxOption1",
    "pf": "frmRequestedList",
    "texti18n": "18n.ess.MyApprovals.frmRequestList.lblAll.text",
    "tooltip": "",
    "wType": "Label",
    "zindex": 1
}