{
  "background_color": "00000000",
  "bg_type": "one",
  "border_color": "424242ff",
  "border_style": "plain",
  "border_type": 0,
  "border_width": 0,
  "fontSizeInPx": false,
  "font_color": "333333ff",
  "font_name": "Helvetica",
  "font_size": 120,
  "font_style": "normal",
  "font_weight": "normal",
  "ipad": {
    "font_name": "Helvetica",
    "font_size": 140,
    "isForked": true
  },
  "isDefaultSkin": false,
  "kuid": "s5f0651606384d4fb1232f354a210524",
  "tabrcandroid": {
    "font_name": "Helvetica",
    "font_size": 140,
    "isForked": true
  },
  "wType": "Label"
}