{
    "DNDConfig": null,
    "__parentReadjusting__": false,
    "_height_": {
        "type": "string",
        "value": "22%"
    },
    "_left_": {
        "type": "string",
        "value": "9%"
    },
    "_margin_": [
        0,
        0,
        0,
        0
    ],
    "_orientation_": 6,
    "_padding_": [
        0,
        0,
        0,
        0
    ],
    "_percent_": true,
    "_skin_": "sa80b6e96abe4ca2946d5c32060065b6",
    "_top_": {
        "type": "string",
        "value": "43%"
    },
    "_width_": {
        "type": "string",
        "value": "70%"
    },
    "allboxes": [],
    "allowhorizontalbounce": false,
    "allowverticalbounce": true,
    "bounces": true,
    "canUpdateUI": true,
    "children": [],
    "clipbounds": true,
    "containerweight": 100,
    "decelerat": false,
    "dragg": false,
    "enablescrolling": true,
    "horizontalscrollindicator": true,
    "id": "flxRequestTypeSelection",
    "info": null,
    "isvisible": true,
    "kuid": "20d4f8d588cf4aae97b85d2a263d2e55",
    "layouttype": 2,
    "name": "kony.ui.FlexScrollContainer",
    "pagingenabled": false,
    "parent": "flxDelegatedApproverAndRequestType",
    "pf": "frmDelegationRequests",
    "scrolldirection": 2,
    "snapgridsize": 10,
    "snaptogrid": true,
    "track": false,
    "verticalscrollindicator": true,
    "wType": "FlexScrollContainer",
    "widgetalignment": 1,
    "zindex": 1
}