[ {
  "entityTypeId" : "28995b99-4bdf-4c59-959e-6a48ddccee34",
  "id" : "00d9fbb3-86a1-435a-9dab-9dbc9f82031b",
  "name" : "Holiday_Date",
  "description" : "description",
  "dataType" : "string",
  "hasIndex" : false,
  "unique" : true,
  "primarykey" : true,
  "namefield" : false,
  "nullable" : false,
  "custom" : true,
  "createable" : true,
  "updateable" : true,
  "audit" : false,
  "customizable" : false,
  "fieldLength" : 10,
  "fieldOrder" : 0,
  "fieldProperties" : {
    "autoGenerated" : "false"
  }
}, {
  "entityTypeId" : "28995b99-4bdf-4c59-959e-6a48ddccee34",
  "id" : "1c10722f-7103-4dbd-84df-0f4e1afb2f61",
  "name" : "Id",
  "description" : "description",
  "dataType" : "string",
  "hasIndex" : false,
  "unique" : true,
  "primarykey" : false,
  "namefield" : false,
  "nullable" : false,
  "custom" : true,
  "createable" : true,
  "updateable" : true,
  "audit" : false,
  "customizable" : false,
  "fieldLength" : 10,
  "fieldOrder" : 0,
  "fieldProperties" : {
    "autoGenerated" : "false"
  }
}, {
  "entityTypeId" : "28995b99-4bdf-4c59-959e-6a48ddccee34",
  "id" : "60a2d6b5-99ed-4b71-bdd4-8497d8980e2b",
  "name" : "lastmodifiedts",
  "sourceFieldname" : "TIMESTAMP",
  "description" : "VTI: Timestamp",
  "dataType" : "string",
  "hasIndex" : false,
  "unique" : false,
  "primarykey" : false,
  "namefield" : false,
  "nullable" : true,
  "custom" : false,
  "createable" : true,
  "updateable" : true,
  "audit" : false,
  "customizable" : false,
  "fieldLength" : 14,
  "fieldOrder" : 0,
  "fieldProperties" : {
    "autoGenerated" : "false"
  }
}, {
  "entityTypeId" : "28995b99-4bdf-4c59-959e-6a48ddccee34",
  "id" : "9a3f6845-e5c7-49a6-a31e-2ce2bf71a518",
  "name" : "Name",
  "description" : "description",
  "dataType" : "string",
  "hasIndex" : false,
  "unique" : false,
  "primarykey" : false,
  "namefield" : false,
  "nullable" : true,
  "custom" : true,
  "createable" : true,
  "updateable" : true,
  "audit" : false,
  "customizable" : false,
  "fieldLength" : 10,
  "fieldOrder" : 0,
  "fieldProperties" : {
    "autoGenerated" : "false"
  }
}, {
  "entityTypeId" : "28995b99-4bdf-4c59-959e-6a48ddccee34",
  "id" : "ea6da982-b109-432e-8cc8-69f662fba07d",
  "name" : "softdeleteflag",
  "sourceFieldname" : "DELETE_IND",
  "description" : "VTI: Delete local function data",
  "dataType" : "string",
  "hasIndex" : false,
  "unique" : false,
  "primarykey" : false,
  "namefield" : false,
  "nullable" : true,
  "custom" : false,
  "createable" : true,
  "updateable" : true,
  "audit" : false,
  "customizable" : false,
  "fieldLength" : 1,
  "fieldOrder" : 0,
  "fieldProperties" : {
    "autoGenerated" : "false"
  }
}, {
  "entityTypeId" : "28995b99-4bdf-4c59-959e-6a48ddccee34",
  "id" : "fa69625d-6348-4238-9300-4a87ec4bbcfb",
  "name" : "Type",
  "description" : "description",
  "dataType" : "string",
  "hasIndex" : false,
  "unique" : false,
  "primarykey" : false,
  "namefield" : false,
  "nullable" : true,
  "custom" : true,
  "createable" : true,
  "updateable" : true,
  "audit" : false,
  "customizable" : false,
  "fieldLength" : 10,
  "fieldOrder" : 0,
  "fieldProperties" : {
    "autoGenerated" : "false"
  }
} ]