{
    "AS_TextArea_abb379f8d849478386e410101b136fd2": {
        "id": "AS_TextArea_abb379f8d849478386e410101b136fd2",
        "type": "ACTION_SEQUENCE",
        "name": "action_TxtAreaCom",
        "params": [{
            "datatype": "collection",
            "name": "eventobject"
        }],
        "contextObj": {
            "name": "frmApplyLeave",
            "type": "forms",
            "platform": "",
            "KUID": "d218c862ae534edebfc84b906fd5ad61"
        },
        "language": "js",
        "actions": [{
            "id": "ADD_SNIPPET__c39cf9219fda4bde8fa508ac36e20125",
            "type": "ADD_SNIPPET",
            "codeSnippet": "kony.apps.coe.ess.myLeave.applyLeave.onclickoftxtComments();",
            "parentId": null
        }]
    }
}